ModifiedNB/ModifiedNB.py
ModifiedNB/__init__.py
ModifiedNB-0.2.dist-info/METADATA
ModifiedNB-0.2.dist-info/WHEEL
ModifiedNB-0.2.dist-info/top_level.txt
ModifiedNB-0.2.dist-info/RECORD
