Metadata-Version: 2.1
Name: ModifiedNB
Version: 0.2
Summary: Laplace corrected modified naïve bayes model
Home-page: https://github.com/chembl/ModifiedNB/
Author: Eloy Félix
Author-email: eloyfelix@gmail.com
License: MIT
Platform: UNKNOWN
Classifier: License :: OSI Approved :: MIT License
Classifier: Programming Language :: Python :: 3.5
Classifier: Programming Language :: Python :: 3.6
Classifier: Programming Language :: Python :: 3.7
Classifier: Topic :: Scientific/Engineering :: Chemistry
Requires-Dist: scikit-learn (>=0.19.0)
